neuroagent/__init__.py
neuroagent/cell_types.py
neuroagent/resolving.py
neuroagent/schemas.py
neuroagent/utils.py
neuroagent/agents/__init__.py
neuroagent/agents/base_agent.py
neuroagent/agents/simple_agent.py
neuroagent/agents/simple_chat_agent.py
neuroagent/app/__init__.py
neuroagent/app/app_utils.py
neuroagent/app/config.py
neuroagent/app/dependencies.py
neuroagent/app/main.py
neuroagent/app/middleware.py
neuroagent/app/schemas.py
neuroagent/app/routers/__init__.py
neuroagent/app/routers/qa.py
neuroagent/app/routers/database/__init__.py
neuroagent/app/routers/database/schemas.py
neuroagent/app/routers/database/sql.py
neuroagent/app/routers/database/threads.py
neuroagent/app/routers/database/tools.py
neuroagent/multi_agents/__init__.py
neuroagent/multi_agents/base_multi_agent.py
neuroagent/multi_agents/supervisor_multi_agent.py
neuroagent/scripts/__init__.py
neuroagent/scripts/neuroagent_api.py
neuroagent/tools/__init__.py
neuroagent/tools/base_tool.py
neuroagent/tools/bluenaas_tool.py
neuroagent/tools/electrophys_tool.py
neuroagent/tools/get_me_model_tool.py
neuroagent/tools/get_morpho_tool.py
neuroagent/tools/kg_morpho_features_tool.py
neuroagent/tools/literature_search_tool.py
neuroagent/tools/morphology_features_tool.py
neuroagent/tools/resolve_entities_tool.py
neuroagent/tools/traces_tool.py
neuroagent-0.3.3.dist-info/AUTHORS.txt
neuroagent-0.3.3.dist-info/LICENSE.md
neuroagent-0.3.3.dist-info/METADATA
neuroagent-0.3.3.dist-info/WHEEL
neuroagent-0.3.3.dist-info/entry_points.txt
neuroagent-0.3.3.dist-info/top_level.txt
neuroagent-0.3.3.dist-info/RECORD
