Metadata-Version: 2.1
Name: neuroagent
Version: 0.3.3
Summary: Search agent for neuroscience.
Author: Blue Brain Project, EPFL
Requires-Python: >=3.10
License-File: LICENSE.md
License-File: AUTHORS.txt
Requires-Dist: aiosqlite
Requires-Dist: asgi-correlation-id
Requires-Dist: asyncpg
Requires-Dist: bluepyefe
Requires-Dist: efel
Requires-Dist: fastapi
Requires-Dist: langchain
Requires-Dist: langchain-cohere
Requires-Dist: langchain-openai
Requires-Dist: langgraph
Requires-Dist: langgraph-checkpoint-postgres
Requires-Dist: langgraph-checkpoint-sqlite
Requires-Dist: neurom
Requires-Dist: psycopg-binary
Requires-Dist: pydantic-settings
Requires-Dist: python-dotenv
Requires-Dist: python-keycloak
Requires-Dist: sqlalchemy[asyncio]
Requires-Dist: uvicorn
Provides-Extra: dev
Requires-Dist: bandit[toml] ; extra == 'dev'
Requires-Dist: mypy ; extra == 'dev'
Requires-Dist: pytest ; extra == 'dev'
Requires-Dist: pytest-asyncio ; extra == 'dev'
Requires-Dist: pytest-cov ; extra == 'dev'
Requires-Dist: pytest-httpx ; extra == 'dev'
Requires-Dist: responses ; extra == 'dev'
Requires-Dist: ruff ; extra == 'dev'
Requires-Dist: types-requests ; extra == 'dev'
